server_inspector-2.0.1.dist-info/licenses/LICENSE
src/__init__.py
src/colors.py
src/main.py
src/utils.py
src/detectors/__init__.py
src/detectors/base.py
src/detectors/cpu.py
src/detectors/gpu.py
src/detectors/ipmi.py
src/detectors/memory.py
src/detectors/motherboard.py
src/detectors/network.py
src/detectors/storage.py
src/detectors/system.py
src/detectors/usb.py
src/parsers/__init__.py
src/parsers/iommu.py
src/parsers/pci.py
server_inspector-2.0.1.dist-info/METADATA
server_inspector-2.0.1.dist-info/WHEEL
server_inspector-2.0.1.dist-info/entry_points.txt
server_inspector-2.0.1.dist-info/top_level.txt
server_inspector-2.0.1.dist-info/RECORD
