Metadata-Version: 2.4
Name: server-inspector
Version: 2.0.1
Summary: Hardware detection and inventory for server
Author: Casa Eureka
License: AGPL-3.0-or-later
Project-URL: Homepage, https://github.com/casaeureka/server-inspector
Project-URL: Repository, https://github.com/casaeureka/server-inspector
Requires-Python: >=3.13
License-File: LICENSE
Requires-Dist: psutil>=5.9.0
Requires-Dist: py-cpuinfo>=9.0.0
Requires-Dist: pyudev>=0.24.0
Requires-Dist: netifaces>=0.11.0
Dynamic: license-file
